zstd.cp37-win32.pyd
zstd-1.5.7.3.dist-info/LICENSE
zstd-1.5.7.3.dist-info/METADATA
zstd-1.5.7.3.dist-info/WHEEL
zstd-1.5.7.3.dist-info/top_level.txt
zstd-1.5.7.3.dist-info/RECORD
