Metadata-Version: 2.1
Name: zstd
Version: 1.5.7.3
Summary: ZSTD Bindings for Python
Home-page: https://github.com/sergey-dryabzhinsky/python-zstd
Author: Sergey Dryabzhinsky, Anton Stuk
Author-email: sergey.dryabzhinsky@gmail.com
Maintainer: Sergey Dryabzhinsky
Maintainer-email: sergey.dryabzhinsky@gmail.com
License: BSD
Keywords: zstd,zstandard,compression
Classifier: Intended Audience :: Developers
Classifier: Development Status :: 5 - Production/Stable
Classifier: Operating System :: POSIX
Classifier: Programming Language :: C
Classifier: Programming Language :: Python
Classifier: Programming Language :: Python :: 2.7
Classifier: Programming Language :: Python :: 3.4
Classifier: Programming Language :: Python :: 3.5
Classifier: Programming Language :: Python :: 3.6
Classifier: Programming Language :: Python :: 3.7
Classifier: Programming Language :: Python :: 3.8
Classifier: Programming Language :: Python :: 3.9
Classifier: Programming Language :: Python :: 3.10
Classifier: Programming Language :: Python :: 3.11
Classifier: Programming Language :: Python :: 3.12
Classifier: Programming Language :: Python :: 3.13
Classifier: Programming Language :: Python :: 3.14
Classifier: Programming Language :: Python :: 3.15
License-File: LICENSE
